daltonize/__init__.py
daltonize/daltonize.py
daltonize-0.2.0.dist-info/COPYING
daltonize-0.2.0.dist-info/METADATA
daltonize-0.2.0.dist-info/WHEEL
daltonize-0.2.0.dist-info/entry_points.txt
daltonize-0.2.0.dist-info/top_level.txt
daltonize-0.2.0.dist-info/RECORD
