Metadata-Version: 2.1
Name: daltonize
Version: 0.2.0
Summary: simulate and correct for color blindness in matplotlib figures and images
Home-page: https://github.com/joergdietrich/daltonize
Author: Jörg Dietrich
Author-email: joerg@joergdietrich.com
Classifier: Programming Language :: Python :: 3
Classifier: License :: OSI Approved :: GNU General Public License v2 (GPLv2)
Classifier: Operating System :: OS Independent
Requires-Python: >=3.6
License-File: COPYING
Requires-Dist: numpy (>=1.9)
Requires-Dist: Pillow
Provides-Extra: test
Requires-Dist: matplotlib (>=3.0.0) ; extra == 'test'
Requires-Dist: pytest ; extra == 'test'
